hubm_cli/__init__.py
hubm_cli/commands/__init__.py
hubm_cli/commands/config_commands.py
hubm_cli/commands/general_commands.py
hubm_cli/commands/group_commands.py
hubm_cli/commands/usb_commands.py
hubm_cli/commands/user_commands.py
hubm_cli/database.py
hubm_cli/exit_codes.py
hubm_cli/main.py
hubm_cli/models.py
hubm_cli/usb_error_monitoring.py
hubm_cli/usb_monitoring.py
hubm_cli/utils/__init__.py
hubm_cli/utils/utils.py
hubm_cli-0.1.17.dist-info/entry_points.txt
hubm_cli-0.1.17.dist-info/LICENSE
hubm_cli-0.1.17.dist-info/METADATA
hubm_cli-0.1.17.dist-info/WHEEL
hubm_cli-0.1.17.dist-info/RECORD
