Metadata-Version: 2.1
Name: hubm_cli
Version: 0.1.17
Summary: 
Home-page: https://github.com/python-poetry/poetry
Author: PrintLine512
Author-email: paralet.games@gmail.com
Requires-Python: >=3.10,<4.0
Classifier: Programming Language :: Python :: 3
Classifier: Programming Language :: Python :: 3.10
Classifier: Programming Language :: Python :: 3.11
Classifier: Programming Language :: Python :: 3.12
Classifier: Programming Language :: Python :: 3.13
Requires-Dist: click (>=8.1.7,<9.0.0)
Requires-Dist: flask (>=3.1.0,<4.0.0)
Requires-Dist: psycopg2 (>=2.9.10,<3.0.0)
Requires-Dist: python-socketio (>=5.11.4,<6.0.0)
Requires-Dist: pyudev (>=0.24.3,<0.25.0)
Requires-Dist: requests (>=2.32.3,<3.0.0)
Requires-Dist: sqlalchemy (>=2.0.36,<3.0.0)
Project-URL: Documentation, https://python-poetry.org/docs/
Project-URL: Repository, https://github.com/python-poetry/poetry
